epijinn/__init__.py
epijinn/version.py
epijinn-0.1.0.dist-info/LICENSE
epijinn-0.1.0.dist-info/METADATA
epijinn-0.1.0.dist-info/WHEEL
epijinn-0.1.0.dist-info/top_level.txt
epijinn-0.1.0.dist-info/RECORD
