Metadata-Version: 2.1
Name: epijinn
Version: 0.1.0
Summary: DNA methylation and restriction
Home-page: UNKNOWN
Author: Peter Vegh
Author-email: UNKNOWN
License: MIT
Keywords: biology
Platform: UNKNOWN
Requires-Dist: biopython
